USG3/__init__.py
USG3/classification.py
USG3/elevation.py
USG3/elevation_data.py
USG3/generate.py
USG3/reprojection.py
USG3/visualize.py
USG3-0.1.dist-info/METADATA
USG3-0.1.dist-info/WHEEL
USG3-0.1.dist-info/top_level.txt
USG3-0.1.dist-info/RECORD
